acplugins4python_example.py
setup.py
acplugins4python/__init__.py
acplugins4python/ac_server_helpers.py
acplugins4python/ac_server_plugin.py
acplugins4python/ac_server_protocol.py
acplugins4python/ac_server_udp_monitor.py
acplugins4python.egg-info/PKG-INFO
acplugins4python.egg-info/SOURCES.txt
acplugins4python.egg-info/dependency_links.txt
acplugins4python.egg-info/not-zip-safe
acplugins4python.egg-info/top_level.txt