Metadata-Version: 1.0
Name: acplugins4python
Version: 0.4
Summary: Python api layer for Assetto Corsa's UDP server API. Developed and tested with AC 1.3.0 on python 3.3.x
Home-page: https://github.com/minolin/acplugins
Author: NeverEatYellowSnow (NEYS)
Author-email: never_eat_yellow_snow@gmx.net
License: BSD
Keywords: Assetto Corsa AC server
Platform: UNKNOWN
